myalbum_dl/__init__.py
myalbum_dl/constants.py
myalbum_dl/myalbum_dl.py
myalbum_dl-0.3.0.dist-info/LICENSE.txt
myalbum_dl-0.3.0.dist-info/METADATA
myalbum_dl-0.3.0.dist-info/WHEEL
myalbum_dl-0.3.0.dist-info/entry_points.txt
myalbum_dl-0.3.0.dist-info/top_level.txt
myalbum_dl-0.3.0.dist-info/RECORD
