Metadata-Version: 2.1
Name: myalbum-dl
Version: 0.3.0
Summary: A command line tool for downloading albums from MyAlbum
Home-page: https://github.com/GBS3/myalbum-dl
Author: Giovanni Salinas
Author-email: gbs3@protonmail.com
License: UNKNOWN
Keywords: myalbum,scraper,download,photos,videos
Platform: UNKNOWN
Classifier: Development Status :: 5 - Production/Stable
Classifier: Programming Language :: Python :: 3.6
Classifier: Programming Language :: Python :: 3.7
Classifier: Programming Language :: Python :: 3.8
Classifier: Programming Language :: Python :: 3.9
Classifier: License :: OSI Approved :: MIT License
Classifier: Operating System :: OS Independent
Requires-Dist: requests
